Metadata-Version: 2.1
Name: reaxpro-wrappers
Version: 3.0.0
Summary: The wrapper of AMS and Zacros drivers for SimPhoNy
Home-page: https://www.esciencecenter.nl/
Author: Netherlands eScience Center, Fraunhofer IWM
Keywords: simphony,cuds,AMS,zacros,SCM
Classifier: Programming Language :: Python :: 3
Classifier: License :: OSI Approved :: GNU Lesser General Public License v3 (LGPLv3)
Classifier: License :: OSI Approved :: BSD License
Classifier: Operating System :: OS Independent
License-File: LICENSE
Requires-Dist: wheel >=0.30.0
Requires-Dist: tk ==0.1.0
Requires-Dist: plams
Requires-Dist: rdflib ==6.2.0
Requires-Dist: osp-core >=3.8.0
Requires-Dist: arcp >=0.2.1
Requires-Dist: minio >=7.1.15
Requires-Dist: pydantic <2.0.0
Requires-Dist: ase >=3.22.1
Provides-Extra: develop
Requires-Dist: pre-commit ; extra == 'develop'
Requires-Dist: pycodestyle ; extra == 'develop'
Requires-Dist: pylint ; extra == 'develop'
Requires-Dist: pytest ; extra == 'develop'
Requires-Dist: pytest-cov ; extra == 'develop'
Requires-Dist: pytest-mock ; extra == 'develop'
Requires-Dist: bumpver ==2021.1114 ; extra == 'develop'
Requires-Dist: dunamai ==1.7.0 ; extra == 'develop'
